{
	"configurations" : 
	[
		{
			"directories" : 
			[
				{
					"build" : ".",
					"childIndexes" : 
					[
						1,
						4
					],
					"hasInstallRule" : true,
					"jsonFile" : "directory-.-Debug-d0094a50bb2071803777.json",
					"minimumCMakeVersion" : 
					{
						"string" : "3.10"
					},
					"projectIndex" : 0,
					"source" : ".",
					"targetIndexes" : 
					[
						0,
						4,
						5,
						6
					]
				},
				{
					"build" : "googletest",
					"childIndexes" : 
					[
						2
					],
					"hasInstallRule" : true,
					"jsonFile" : "directory-googletest-Debug-294c64d4885f2a55f3f7.json",
					"minimumCMakeVersion" : 
					{
						"string" : "3.13"
					},
					"parentIndex" : 0,
					"projectIndex" : 1,
					"source" : "googletest",
					"targetIndexes" : 
					[
						1
					]
				},
				{
					"build" : "googletest/googlemock",
					"childIndexes" : 
					[
						3
					],
					"hasInstallRule" : true,
					"jsonFile" : "directory-googletest.googlemock-Debug-157d9abd7e1468cb63bb.json",
					"minimumCMakeVersion" : 
					{
						"string" : "3.13"
					},
					"parentIndex" : 1,
					"projectIndex" : 2,
					"source" : "googletest/googlemock",
					"targetIndexes" : 
					[
						2,
						7,
						8
					]
				},
				{
					"build" : "googletest/googletest",
					"hasInstallRule" : true,
					"jsonFile" : "directory-googletest.googletest-Debug-6ce0dae44e7815b8440f.json",
					"minimumCMakeVersion" : 
					{
						"string" : "3.13"
					},
					"parentIndex" : 2,
					"projectIndex" : 3,
					"source" : "googletest/googletest",
					"targetIndexes" : 
					[
						3,
						9,
						10
					]
				},
				{
					"build" : "test",
					"jsonFile" : "directory-test-Debug-f18be1977b403cfd1a50.json",
					"minimumCMakeVersion" : 
					{
						"string" : "3.10"
					},
					"parentIndex" : 0,
					"projectIndex" : 0,
					"source" : "test"
				}
			],
			"name" : "Debug",
			"projects" : 
			[
				{
					"childIndexes" : 
					[
						1
					],
					"directoryIndexes" : 
					[
						0,
						4
					],
					"name" : "WarGame",
					"targetIndexes" : 
					[
						0,
						4,
						5,
						6
					]
				},
				{
					"childIndexes" : 
					[
						2
					],
					"directoryIndexes" : 
					[
						1
					],
					"name" : "googletest-distribution",
					"parentIndex" : 0,
					"targetIndexes" : 
					[
						1
					]
				},
				{
					"childIndexes" : 
					[
						3
					],
					"directoryIndexes" : 
					[
						2
					],
					"name" : "gmock",
					"parentIndex" : 1,
					"targetIndexes" : 
					[
						2,
						7,
						8
					]
				},
				{
					"directoryIndexes" : 
					[
						3
					],
					"name" : "gtest",
					"parentIndex" : 2,
					"targetIndexes" : 
					[
						3,
						9,
						10
					]
				}
			],
			"targets" : 
			[
				{
					"directoryIndex" : 0,
					"id" : "ALL_BUILD::@6890427a1f51a3e7e1df",
					"jsonFile" : "target-ALL_BUILD-Debug-ed6735c6c9b0cc4c004b.json",
					"name" : "ALL_BUILD",
					"projectIndex" : 0
				},
				{
					"directoryIndex" : 1,
					"id" : "ALL_BUILD::@b3026ea3adfb7c2366ee",
					"jsonFile" : "target-ALL_BUILD-Debug-5ab3997f2bc628a40dc6.json",
					"name" : "ALL_BUILD",
					"projectIndex" : 1
				},
				{
					"directoryIndex" : 2,
					"id" : "ALL_BUILD::@d68da25237a7ca2351af",
					"jsonFile" : "target-ALL_BUILD-Debug-1ae43c093377da5d39cc.json",
					"name" : "ALL_BUILD",
					"projectIndex" : 2
				},
				{
					"directoryIndex" : 3,
					"id" : "ALL_BUILD::@f95b5c00bd49b3b4698d",
					"jsonFile" : "target-ALL_BUILD-Debug-ca74f66954ca4bd1a938.json",
					"name" : "ALL_BUILD",
					"projectIndex" : 3
				},
				{
					"directoryIndex" : 0,
					"id" : "WarGame::@6890427a1f51a3e7e1df",
					"jsonFile" : "target-WarGame-Debug-8edb037e60c9c48788c1.json",
					"name" : "WarGame",
					"projectIndex" : 0
				},
				{
					"directoryIndex" : 0,
					"id" : "WarGame_lib::@6890427a1f51a3e7e1df",
					"jsonFile" : "target-WarGame_lib-Debug-4039cafc8c47b6ccdeca.json",
					"name" : "WarGame_lib",
					"projectIndex" : 0
				},
				{
					"directoryIndex" : 0,
					"id" : "ZERO_CHECK::@6890427a1f51a3e7e1df",
					"jsonFile" : "target-ZERO_CHECK-Debug-f584c6b3807fed7dc060.json",
					"name" : "ZERO_CHECK",
					"projectIndex" : 0
				},
				{
					"directoryIndex" : 2,
					"id" : "gmock::@d68da25237a7ca2351af",
					"jsonFile" : "target-gmock-Debug-437b05f51f71d20c4295.json",
					"name" : "gmock",
					"projectIndex" : 2
				},
				{
					"directoryIndex" : 2,
					"id" : "gmock_main::@d68da25237a7ca2351af",
					"jsonFile" : "target-gmock_main-Debug-69842ccda2a6e5bd2cd1.json",
					"name" : "gmock_main",
					"projectIndex" : 2
				},
				{
					"directoryIndex" : 3,
					"id" : "gtest::@f95b5c00bd49b3b4698d",
					"jsonFile" : "target-gtest-Debug-9a7143a296bf6ff83361.json",
					"name" : "gtest",
					"projectIndex" : 3
				},
				{
					"directoryIndex" : 3,
					"id" : "gtest_main::@f95b5c00bd49b3b4698d",
					"jsonFile" : "target-gtest_main-Debug-cf40f99878e84ce2abf6.json",
					"name" : "gtest_main",
					"projectIndex" : 3
				}
			]
		},
		{
			"directories" : 
			[
				{
					"build" : ".",
					"childIndexes" : 
					[
						1,
						4
					],
					"hasInstallRule" : true,
					"jsonFile" : "directory-.-Release-d0094a50bb2071803777.json",
					"minimumCMakeVersion" : 
					{
						"string" : "3.10"
					},
					"projectIndex" : 0,
					"source" : ".",
					"targetIndexes" : 
					[
						0,
						4,
						5,
						6
					]
				},
				{
					"build" : "googletest",
					"childIndexes" : 
					[
						2
					],
					"hasInstallRule" : true,
					"jsonFile" : "directory-googletest-Release-294c64d4885f2a55f3f7.json",
					"minimumCMakeVersion" : 
					{
						"string" : "3.13"
					},
					"parentIndex" : 0,
					"projectIndex" : 1,
					"source" : "googletest",
					"targetIndexes" : 
					[
						1
					]
				},
				{
					"build" : "googletest/googlemock",
					"childIndexes" : 
					[
						3
					],
					"hasInstallRule" : true,
					"jsonFile" : "directory-googletest.googlemock-Release-055d7de5d16914abb69f.json",
					"minimumCMakeVersion" : 
					{
						"string" : "3.13"
					},
					"parentIndex" : 1,
					"projectIndex" : 2,
					"source" : "googletest/googlemock",
					"targetIndexes" : 
					[
						2,
						7,
						8
					]
				},
				{
					"build" : "googletest/googletest",
					"hasInstallRule" : true,
					"jsonFile" : "directory-googletest.googletest-Release-e6d5e24dc73e6a99334c.json",
					"minimumCMakeVersion" : 
					{
						"string" : "3.13"
					},
					"parentIndex" : 2,
					"projectIndex" : 3,
					"source" : "googletest/googletest",
					"targetIndexes" : 
					[
						3,
						9,
						10
					]
				},
				{
					"build" : "test",
					"jsonFile" : "directory-test-Release-f18be1977b403cfd1a50.json",
					"minimumCMakeVersion" : 
					{
						"string" : "3.10"
					},
					"parentIndex" : 0,
					"projectIndex" : 0,
					"source" : "test"
				}
			],
			"name" : "Release",
			"projects" : 
			[
				{
					"childIndexes" : 
					[
						1
					],
					"directoryIndexes" : 
					[
						0,
						4
					],
					"name" : "WarGame",
					"targetIndexes" : 
					[
						0,
						4,
						5,
						6
					]
				},
				{
					"childIndexes" : 
					[
						2
					],
					"directoryIndexes" : 
					[
						1
					],
					"name" : "googletest-distribution",
					"parentIndex" : 0,
					"targetIndexes" : 
					[
						1
					]
				},
				{
					"childIndexes" : 
					[
						3
					],
					"directoryIndexes" : 
					[
						2
					],
					"name" : "gmock",
					"parentIndex" : 1,
					"targetIndexes" : 
					[
						2,
						7,
						8
					]
				},
				{
					"directoryIndexes" : 
					[
						3
					],
					"name" : "gtest",
					"parentIndex" : 2,
					"targetIndexes" : 
					[
						3,
						9,
						10
					]
				}
			],
			"targets" : 
			[
				{
					"directoryIndex" : 0,
					"id" : "ALL_BUILD::@6890427a1f51a3e7e1df",
					"jsonFile" : "target-ALL_BUILD-Release-ed6735c6c9b0cc4c004b.json",
					"name" : "ALL_BUILD",
					"projectIndex" : 0
				},
				{
					"directoryIndex" : 1,
					"id" : "ALL_BUILD::@b3026ea3adfb7c2366ee",
					"jsonFile" : "target-ALL_BUILD-Release-5ab3997f2bc628a40dc6.json",
					"name" : "ALL_BUILD",
					"projectIndex" : 1
				},
				{
					"directoryIndex" : 2,
					"id" : "ALL_BUILD::@d68da25237a7ca2351af",
					"jsonFile" : "target-ALL_BUILD-Release-1ae43c093377da5d39cc.json",
					"name" : "ALL_BUILD",
					"projectIndex" : 2
				},
				{
					"directoryIndex" : 3,
					"id" : "ALL_BUILD::@f95b5c00bd49b3b4698d",
					"jsonFile" : "target-ALL_BUILD-Release-ca74f66954ca4bd1a938.json",
					"name" : "ALL_BUILD",
					"projectIndex" : 3
				},
				{
					"directoryIndex" : 0,
					"id" : "WarGame::@6890427a1f51a3e7e1df",
					"jsonFile" : "target-WarGame-Release-272009e0f0e6ecb6d6f6.json",
					"name" : "WarGame",
					"projectIndex" : 0
				},
				{
					"directoryIndex" : 0,
					"id" : "WarGame_lib::@6890427a1f51a3e7e1df",
					"jsonFile" : "target-WarGame_lib-Release-c7e5424c0a19909950a3.json",
					"name" : "WarGame_lib",
					"projectIndex" : 0
				},
				{
					"directoryIndex" : 0,
					"id" : "ZERO_CHECK::@6890427a1f51a3e7e1df",
					"jsonFile" : "target-ZERO_CHECK-Release-f584c6b3807fed7dc060.json",
					"name" : "ZERO_CHECK",
					"projectIndex" : 0
				},
				{
					"directoryIndex" : 2,
					"id" : "gmock::@d68da25237a7ca2351af",
					"jsonFile" : "target-gmock-Release-7ac622e4e6ae0881ffd6.json",
					"name" : "gmock",
					"projectIndex" : 2
				},
				{
					"directoryIndex" : 2,
					"id" : "gmock_main::@d68da25237a7ca2351af",
					"jsonFile" : "target-gmock_main-Release-d2e974214862c7b3e31e.json",
					"name" : "gmock_main",
					"projectIndex" : 2
				},
				{
					"directoryIndex" : 3,
					"id" : "gtest::@f95b5c00bd49b3b4698d",
					"jsonFile" : "target-gtest-Release-0e4d5fce3c8b434bde66.json",
					"name" : "gtest",
					"projectIndex" : 3
				},
				{
					"directoryIndex" : 3,
					"id" : "gtest_main::@f95b5c00bd49b3b4698d",
					"jsonFile" : "target-gtest_main-Release-d4de4678a7a0a1d7d683.json",
					"name" : "gtest_main",
					"projectIndex" : 3
				}
			]
		},
		{
			"directories" : 
			[
				{
					"build" : ".",
					"childIndexes" : 
					[
						1,
						4
					],
					"hasInstallRule" : true,
					"jsonFile" : "directory-.-MinSizeRel-d0094a50bb2071803777.json",
					"minimumCMakeVersion" : 
					{
						"string" : "3.10"
					},
					"projectIndex" : 0,
					"source" : ".",
					"targetIndexes" : 
					[
						0,
						4,
						5,
						6
					]
				},
				{
					"build" : "googletest",
					"childIndexes" : 
					[
						2
					],
					"hasInstallRule" : true,
					"jsonFile" : "directory-googletest-MinSizeRel-294c64d4885f2a55f3f7.json",
					"minimumCMakeVersion" : 
					{
						"string" : "3.13"
					},
					"parentIndex" : 0,
					"projectIndex" : 1,
					"source" : "googletest",
					"targetIndexes" : 
					[
						1
					]
				},
				{
					"build" : "googletest/googlemock",
					"childIndexes" : 
					[
						3
					],
					"hasInstallRule" : true,
					"jsonFile" : "directory-googletest.googlemock-MinSizeRel-bce85e5311e8f5984e06.json",
					"minimumCMakeVersion" : 
					{
						"string" : "3.13"
					},
					"parentIndex" : 1,
					"projectIndex" : 2,
					"source" : "googletest/googlemock",
					"targetIndexes" : 
					[
						2,
						7,
						8
					]
				},
				{
					"build" : "googletest/googletest",
					"hasInstallRule" : true,
					"jsonFile" : "directory-googletest.googletest-MinSizeRel-bd70274ba9b5d698c686.json",
					"minimumCMakeVersion" : 
					{
						"string" : "3.13"
					},
					"parentIndex" : 2,
					"projectIndex" : 3,
					"source" : "googletest/googletest",
					"targetIndexes" : 
					[
						3,
						9,
						10
					]
				},
				{
					"build" : "test",
					"jsonFile" : "directory-test-MinSizeRel-f18be1977b403cfd1a50.json",
					"minimumCMakeVersion" : 
					{
						"string" : "3.10"
					},
					"parentIndex" : 0,
					"projectIndex" : 0,
					"source" : "test"
				}
			],
			"name" : "MinSizeRel",
			"projects" : 
			[
				{
					"childIndexes" : 
					[
						1
					],
					"directoryIndexes" : 
					[
						0,
						4
					],
					"name" : "WarGame",
					"targetIndexes" : 
					[
						0,
						4,
						5,
						6
					]
				},
				{
					"childIndexes" : 
					[
						2
					],
					"directoryIndexes" : 
					[
						1
					],
					"name" : "googletest-distribution",
					"parentIndex" : 0,
					"targetIndexes" : 
					[
						1
					]
				},
				{
					"childIndexes" : 
					[
						3
					],
					"directoryIndexes" : 
					[
						2
					],
					"name" : "gmock",
					"parentIndex" : 1,
					"targetIndexes" : 
					[
						2,
						7,
						8
					]
				},
				{
					"directoryIndexes" : 
					[
						3
					],
					"name" : "gtest",
					"parentIndex" : 2,
					"targetIndexes" : 
					[
						3,
						9,
						10
					]
				}
			],
			"targets" : 
			[
				{
					"directoryIndex" : 0,
					"id" : "ALL_BUILD::@6890427a1f51a3e7e1df",
					"jsonFile" : "target-ALL_BUILD-MinSizeRel-ed6735c6c9b0cc4c004b.json",
					"name" : "ALL_BUILD",
					"projectIndex" : 0
				},
				{
					"directoryIndex" : 1,
					"id" : "ALL_BUILD::@b3026ea3adfb7c2366ee",
					"jsonFile" : "target-ALL_BUILD-MinSizeRel-5ab3997f2bc628a40dc6.json",
					"name" : "ALL_BUILD",
					"projectIndex" : 1
				},
				{
					"directoryIndex" : 2,
					"id" : "ALL_BUILD::@d68da25237a7ca2351af",
					"jsonFile" : "target-ALL_BUILD-MinSizeRel-1ae43c093377da5d39cc.json",
					"name" : "ALL_BUILD",
					"projectIndex" : 2
				},
				{
					"directoryIndex" : 3,
					"id" : "ALL_BUILD::@f95b5c00bd49b3b4698d",
					"jsonFile" : "target-ALL_BUILD-MinSizeRel-ca74f66954ca4bd1a938.json",
					"name" : "ALL_BUILD",
					"projectIndex" : 3
				},
				{
					"directoryIndex" : 0,
					"id" : "WarGame::@6890427a1f51a3e7e1df",
					"jsonFile" : "target-WarGame-MinSizeRel-e583136bda3c5988bde7.json",
					"name" : "WarGame",
					"projectIndex" : 0
				},
				{
					"directoryIndex" : 0,
					"id" : "WarGame_lib::@6890427a1f51a3e7e1df",
					"jsonFile" : "target-WarGame_lib-MinSizeRel-6f0e49e3f98fef9d61f1.json",
					"name" : "WarGame_lib",
					"projectIndex" : 0
				},
				{
					"directoryIndex" : 0,
					"id" : "ZERO_CHECK::@6890427a1f51a3e7e1df",
					"jsonFile" : "target-ZERO_CHECK-MinSizeRel-f584c6b3807fed7dc060.json",
					"name" : "ZERO_CHECK",
					"projectIndex" : 0
				},
				{
					"directoryIndex" : 2,
					"id" : "gmock::@d68da25237a7ca2351af",
					"jsonFile" : "target-gmock-MinSizeRel-0c026f95f278ecd4a1ae.json",
					"name" : "gmock",
					"projectIndex" : 2
				},
				{
					"directoryIndex" : 2,
					"id" : "gmock_main::@d68da25237a7ca2351af",
					"jsonFile" : "target-gmock_main-MinSizeRel-0d2fb5944a2904dfb5a4.json",
					"name" : "gmock_main",
					"projectIndex" : 2
				},
				{
					"directoryIndex" : 3,
					"id" : "gtest::@f95b5c00bd49b3b4698d",
					"jsonFile" : "target-gtest-MinSizeRel-4d56cc05539b484ad784.json",
					"name" : "gtest",
					"projectIndex" : 3
				},
				{
					"directoryIndex" : 3,
					"id" : "gtest_main::@f95b5c00bd49b3b4698d",
					"jsonFile" : "target-gtest_main-MinSizeRel-44c85a7aeb684f0ea6fa.json",
					"name" : "gtest_main",
					"projectIndex" : 3
				}
			]
		},
		{
			"directories" : 
			[
				{
					"build" : ".",
					"childIndexes" : 
					[
						1,
						4
					],
					"hasInstallRule" : true,
					"jsonFile" : "directory-.-RelWithDebInfo-d0094a50bb2071803777.json",
					"minimumCMakeVersion" : 
					{
						"string" : "3.10"
					},
					"projectIndex" : 0,
					"source" : ".",
					"targetIndexes" : 
					[
						0,
						4,
						5,
						6
					]
				},
				{
					"build" : "googletest",
					"childIndexes" : 
					[
						2
					],
					"hasInstallRule" : true,
					"jsonFile" : "directory-googletest-RelWithDebInfo-294c64d4885f2a55f3f7.json",
					"minimumCMakeVersion" : 
					{
						"string" : "3.13"
					},
					"parentIndex" : 0,
					"projectIndex" : 1,
					"source" : "googletest",
					"targetIndexes" : 
					[
						1
					]
				},
				{
					"build" : "googletest/googlemock",
					"childIndexes" : 
					[
						3
					],
					"hasInstallRule" : true,
					"jsonFile" : "directory-googletest.googlemock-RelWithDebInfo-364a9df926c502949276.json",
					"minimumCMakeVersion" : 
					{
						"string" : "3.13"
					},
					"parentIndex" : 1,
					"projectIndex" : 2,
					"source" : "googletest/googlemock",
					"targetIndexes" : 
					[
						2,
						7,
						8
					]
				},
				{
					"build" : "googletest/googletest",
					"hasInstallRule" : true,
					"jsonFile" : "directory-googletest.googletest-RelWithDebInfo-ad76c84af09780d57f75.json",
					"minimumCMakeVersion" : 
					{
						"string" : "3.13"
					},
					"parentIndex" : 2,
					"projectIndex" : 3,
					"source" : "googletest/googletest",
					"targetIndexes" : 
					[
						3,
						9,
						10
					]
				},
				{
					"build" : "test",
					"jsonFile" : "directory-test-RelWithDebInfo-f18be1977b403cfd1a50.json",
					"minimumCMakeVersion" : 
					{
						"string" : "3.10"
					},
					"parentIndex" : 0,
					"projectIndex" : 0,
					"source" : "test"
				}
			],
			"name" : "RelWithDebInfo",
			"projects" : 
			[
				{
					"childIndexes" : 
					[
						1
					],
					"directoryIndexes" : 
					[
						0,
						4
					],
					"name" : "WarGame",
					"targetIndexes" : 
					[
						0,
						4,
						5,
						6
					]
				},
				{
					"childIndexes" : 
					[
						2
					],
					"directoryIndexes" : 
					[
						1
					],
					"name" : "googletest-distribution",
					"parentIndex" : 0,
					"targetIndexes" : 
					[
						1
					]
				},
				{
					"childIndexes" : 
					[
						3
					],
					"directoryIndexes" : 
					[
						2
					],
					"name" : "gmock",
					"parentIndex" : 1,
					"targetIndexes" : 
					[
						2,
						7,
						8
					]
				},
				{
					"directoryIndexes" : 
					[
						3
					],
					"name" : "gtest",
					"parentIndex" : 2,
					"targetIndexes" : 
					[
						3,
						9,
						10
					]
				}
			],
			"targets" : 
			[
				{
					"directoryIndex" : 0,
					"id" : "ALL_BUILD::@6890427a1f51a3e7e1df",
					"jsonFile" : "target-ALL_BUILD-RelWithDebInfo-ed6735c6c9b0cc4c004b.json",
					"name" : "ALL_BUILD",
					"projectIndex" : 0
				},
				{
					"directoryIndex" : 1,
					"id" : "ALL_BUILD::@b3026ea3adfb7c2366ee",
					"jsonFile" : "target-ALL_BUILD-RelWithDebInfo-5ab3997f2bc628a40dc6.json",
					"name" : "ALL_BUILD",
					"projectIndex" : 1
				},
				{
					"directoryIndex" : 2,
					"id" : "ALL_BUILD::@d68da25237a7ca2351af",
					"jsonFile" : "target-ALL_BUILD-RelWithDebInfo-1ae43c093377da5d39cc.json",
					"name" : "ALL_BUILD",
					"projectIndex" : 2
				},
				{
					"directoryIndex" : 3,
					"id" : "ALL_BUILD::@f95b5c00bd49b3b4698d",
					"jsonFile" : "target-ALL_BUILD-RelWithDebInfo-ca74f66954ca4bd1a938.json",
					"name" : "ALL_BUILD",
					"projectIndex" : 3
				},
				{
					"directoryIndex" : 0,
					"id" : "WarGame::@6890427a1f51a3e7e1df",
					"jsonFile" : "target-WarGame-RelWithDebInfo-8c6c3260034d644a2255.json",
					"name" : "WarGame",
					"projectIndex" : 0
				},
				{
					"directoryIndex" : 0,
					"id" : "WarGame_lib::@6890427a1f51a3e7e1df",
					"jsonFile" : "target-WarGame_lib-RelWithDebInfo-c993d3f8c37d1b244461.json",
					"name" : "WarGame_lib",
					"projectIndex" : 0
				},
				{
					"directoryIndex" : 0,
					"id" : "ZERO_CHECK::@6890427a1f51a3e7e1df",
					"jsonFile" : "target-ZERO_CHECK-RelWithDebInfo-f584c6b3807fed7dc060.json",
					"name" : "ZERO_CHECK",
					"projectIndex" : 0
				},
				{
					"directoryIndex" : 2,
					"id" : "gmock::@d68da25237a7ca2351af",
					"jsonFile" : "target-gmock-RelWithDebInfo-5bb873138e0da70e5a2d.json",
					"name" : "gmock",
					"projectIndex" : 2
				},
				{
					"directoryIndex" : 2,
					"id" : "gmock_main::@d68da25237a7ca2351af",
					"jsonFile" : "target-gmock_main-RelWithDebInfo-1a0f271e20a6a7ce4c4d.json",
					"name" : "gmock_main",
					"projectIndex" : 2
				},
				{
					"directoryIndex" : 3,
					"id" : "gtest::@f95b5c00bd49b3b4698d",
					"jsonFile" : "target-gtest-RelWithDebInfo-82be95b4e71585399419.json",
					"name" : "gtest",
					"projectIndex" : 3
				},
				{
					"directoryIndex" : 3,
					"id" : "gtest_main::@f95b5c00bd49b3b4698d",
					"jsonFile" : "target-gtest_main-RelWithDebInfo-642d8f0637797b00fe0c.json",
					"name" : "gtest_main",
					"projectIndex" : 3
				}
			]
		}
	],
	"kind" : "codemodel",
	"paths" : 
	{
		"build" : "D:/WarGame/build",
		"source" : "D:/WarGame"
	},
	"version" : 
	{
		"major" : 2,
		"minor" : 4
	}
}
